Workbook
Name aporte: Slv_Invest!$C$18
Name patrimonio: Slv_Invest!$C$21
Name qtd_anos: Slv_Invest!$C$19
Name rendimento_carteira: Slv_Invest!$C$13
Name salario: Slv_Invest!$C$12
Name sugestao_invest: Slv_Invest!$C$14
Name taxa_mensal: Slv_Invest!$C$20

Sheet Slv_Invest
B11: CONFIGURAÇÕES | E11: CENÁRIOS | G11: Dividendo
B12: Salário | C12: 2350 | E12: Em 2 anos | F12: =FV($C$20,$A19*12,$C$18*-1) -> 19061.605 | G12: =F12*rendimento_carteira -> 114.36963
B13: Redimento Carteira | C13: 0.006 | E13: Em 5 anos | F13: =FV($C$20,$A20*12,$C$18*-1) -> 58662.814 | G13: =F13*rendimento_carteira -> 351.97688
B14: Sugestão de Investimento | C14: =C12*30% -> 705 | E14: Em 8 anos | F14: =FV($C$20,$A21*12,$C$18*-1) -> 116961.24 | G14: =F14*rendimento_carteira -> 701.76745
E15: Em 10 anos | F15: =FV($C$20,$A22*12,$C$18*-1) -> 170420.37 | G15: =F15*rendimento_carteira -> 1022.5222
E16: Em 12 anos | F16: =FV($C$20,$A23*12,$C$18*-1) -> 239601.46 | G16: =F16*rendimento_carteira -> 1437.6088
B17: INVESTIMENTO MENSAL
B18: Quanto Investir por Mês | C18: 700
A19: 2 | B19: Por Quantos Anos | C19: 5 | E19: TIPO DE FII | F19: PERCENTUAL SEGERIDO | G19: VALORES
A20: 5 | B20: Taxa de Rendimento Mensal | C20: 0.0108 | E20: PAPEL | F20: =VLOOKUP($C$25&"-"&E20,apoio!$A:$D,4,FALSE) -> 0.5 | G20: =F20*$C$26 -> 350
A21: 8 | B21: Patrimônio Acumulado | C21: =FV(taxa_mensal,qtd_anos*12,aporte*-1) -> 58662.814 | E21: TIJOLO | F21: =VLOOKUP($C$25&"-"&E21,apoio!$A:$D,4,FALSE) -> 0.1 | G21: =F21*$C$26 -> 70
A22: 10 | B22: Dividendo Mensal | C22: =patrimonio*rendimento_carteira -> 351.97688 | E22: HIBRIDOS | F22: =VLOOKUP($C$25&"-"&E22,apoio!$A:$D,4,FALSE) -> 0.05 | G22: =F22*$C$26 -> 35
A23: 12 | E23: FOFs | F23: =VLOOKUP($C$25&"-"&E23,apoio!$A:$D,4,FALSE) -> 0.05 | G23: =F23*$C$26 -> 35
E24: DESENVOLVIMENTO | F24: =VLOOKUP($C$25&"-"&E24,apoio!$A:$D,4,FALSE) -> 0.2 | G24: =F24*$C$26 -> 140
B25: PERFIL | C25: Agressivo | E25: HOTELARIAS | F25: =VLOOKUP($C$25&"-"&E25,apoio!$A:$D,4,FALSE) -> 0.1 | G25: =F25*$C$26 -> 70
B26: Valor a ser investido por mês | C26: =aporte -> 700 | G26: =SUM(G20:G25) -> 700

Sheet apoio
A4: CHAVE | B4: PERFIL | C4: TIPO DE FII | D4: %
A5: =B5&"-"&C5 -> Conservador-PAPEL | B5: Conservador | C5: PAPEL | D5: 0.3 | G5: %
A6: =B6&"-"&C6 -> Conservador-TIJOLO | B6: Conservador | C6: TIJOLO | D6: 0.5 | F6: Moderado-TIJOLO | G6: =VLOOKUP(F6,$A:$D,4,FALSE) -> 0.35
A7: =B7&"-"&C7 -> Conservador-HIBRIDOS | B7: Conservador | C7: HIBRIDOS | D7: 0.1
A8: =B8&"-"&C8 -> Conservador-FOFs | B8: Conservador | C8: FOFs | D8: 0.1
A9: =B9&"-"&C9 -> Conservador-DESENVOLVIMENTO | B9: Conservador | C9: DESENVOLVIMENTO | D9: 0
A10: =B10&"-"&C10 -> Conservador-HOTELARIAS | B10: Conservador | C10: HOTELARIAS | D10: 0
A11: =B11&"-"&C11 -> Moderado-PAPEL | B11: Moderado | C11: PAPEL | D11: 0.32
A12: =B12&"-"&C12 -> Moderado-TIJOLO | B12: Moderado | C12: TIJOLO | D12: 0.35
A13: =B13&"-"&C13 -> Moderado-HIBRIDOS | B13: Moderado | C13: HIBRIDOS | D13: 0.08
A14: =B14&"-"&C14 -> Moderado-FOFs | B14: Moderado | C14: FOFs | D14: 0.05
A15: =B15&"-"&C15 -> Moderado-DESENVOLVIMENTO | B15: Moderado | C15: DESENVOLVIMENTO | D15: 0.1
A16: =B16&"-"&C16 -> Moderado-HOTELARIAS | B16: Moderado | C16: HOTELARIAS | D16: 0.1
A17: =B17&"-"&C17 -> Agressivo-PAPEL | B17: Agressivo | C17: PAPEL | D17: 0.5
A18: =B18&"-"&C18 -> Agressivo-TIJOLO | B18: Agressivo | C18: TIJOLO | D18: 0.1
... A22: =B22&"-"&C22 -> Agressivo-HOTELARIAS | B22: Agressivo | C22: HOTELARIAS | D22: 0.1
